scuttlesort/__init__.py
scuttlesort/demo.py
scuttlesort-0.0.9.dist-info/LICENSE
scuttlesort-0.0.9.dist-info/METADATA
scuttlesort-0.0.9.dist-info/WHEEL
scuttlesort-0.0.9.dist-info/top_level.txt
scuttlesort-0.0.9.dist-info/RECORD
