Metadata-Version: 2.1
Name: scuttlesort
Version: 0.0.9
Summary: ScuttleSort - incremental convergent topological sort for Secure Scuttlebutt
Home-page: https://github.com/tschudin/scuttlesort
Author: Christian Tschudin
Author-email: christian.tschudin@unibas.ch
Classifier: Programming Language :: Python :: 3
Classifier: License :: OSI Approved :: MIT License
Classifier: Operating System :: OS Independent
Requires-Python: >=3.7
License-File: LICENSE
